astro_ssptools-2.1.1.dist-info/licenses/LICENSE
ssptools/Kroupa.py
ssptools/__init__.py
ssptools/evolve_mf.py
ssptools/ifmr.py
ssptools/kicks.py
ssptools/masses.py
ssptools/sev.py
ssptools/data/ifmr/README.md
ssptools/data/ifmr/COSMIC_delayed/IFMR_FEH+0.00.dat
ssptools/data/ifmr/COSMIC_delayed/IFMR_FEH+0.01.dat
ssptools/data/ifmr/COSMIC_delayed/IFMR_FEH+0.02.dat
ssptools/data/ifmr/COSMIC_delayed/IFMR_FEH+0.03.dat
ssptools/data/ifmr/COSMIC_delayed/IFMR_FEH+0.04.dat
ssptools/data/ifmr/COSMIC_delayed/IFMR_FEH+0.05.dat
ssptools/data/ifmr/COSMIC_delayed/IFMR_FEH+0.06.dat
ssptools/data/ifmr/COSMIC_delayed/IFMR_FEH+0.07.dat
ssptools/data/ifmr/COSMIC_delayed/IFMR_FEH+0.08.dat
ssptools/data/ifmr/COSMIC_delayed/IFMR_FEH+0.09.dat
ssptools/data/ifmr/COSMIC_delayed/IFMR_FEH+0.10.dat
ssptools/data/ifmr/COSMIC_delayed/IFMR_FEH+0.11.dat
ssptools/data/ifmr/COSMIC_delayed/IFMR_FEH+0.12.dat
ssptools/data/ifmr/COSMIC_delayed/IFMR_FEH+0.13.dat
ssptools/data/ifmr/COSMIC_delayed/IFMR_FEH+0.14.dat
ssptools/data/ifmr/COSMIC_delayed/IFMR_FEH+0.15.dat
ssptools/data/ifmr/COSMIC_delayed/IFMR_FEH+0.16.dat
ssptools/data/ifmr/COSMIC_delayed/IFMR_FEH+0.17.dat
ssptools/data/ifmr/COSMIC_delayed/IFMR_FEH+0.18.dat
ssptools/data/ifmr/COSMIC_delayed/IFMR_FEH+0.19.dat
ssptools/data/ifmr/COSMIC_delayed/IFMR_FEH+0.20.dat
ssptools/data/ifmr/COSMIC_delayed/IFMR_FEH+0.21.dat
ssptools/data/ifmr/COSMIC_delayed/IFMR_FEH+0.22.dat
ssptools/data/ifmr/COSMIC_delayed/IFMR_FEH+0.23.dat
ssptools/data/ifmr/COSMIC_delayed/IFMR_FEH+0.24.dat
ssptools/data/ifmr/COSMIC_delayed/IFMR_FEH+0.25.dat
ssptools/data/ifmr/COSMIC_delayed/IFMR_FEH+0.26.dat
ssptools/data/ifmr/COSMIC_delayed/IFMR_FEH+0.27.dat
ssptools/data/ifmr/COSMIC_delayed/IFMR_FEH+0.28.dat
ssptools/data/ifmr/COSMIC_delayed/IFMR_FEH+0.29.dat
ssptools/data/ifmr/COSMIC_delayed/IFMR_FEH+0.30.dat
ssptools/data/ifmr/COSMIC_delayed/IFMR_FEH+0.31.dat
ssptools/data/ifmr/COSMIC_delayed/IFMR_FEH+0.32.dat
ssptools/data/ifmr/COSMIC_delayed/IFMR_FEH+0.33.dat
ssptools/data/ifmr/COSMIC_delayed/IFMR_FEH+0.34.dat
astro_ssptools-2.1.1.dist-info/METADATA
astro_ssptools-2.1.1.dist-info/WHEEL
astro_ssptools-2.1.1.dist-info/top_level.txt
astro_ssptools-2.1.1.dist-info/RECORD
