Metadata-Version: 2.4
Name: astro-ssptools
Version: 2.1.1
Summary: Simple Stellar Population Tools
Author-email: Eduardo Balbinot <eduardo.balbinot@gmail.com>, Nolan Dickson <nolan.dickson@smu.ca>, Peter Smith <smith.peter.902@gmail.com>, Mark Gieles <m.gieles@surrey.ac.uk>, Miklos Peuten <m.peuten@surrey.ac.uk>
License: MIT License
Project-URL: repository, https://github.com/SMU-clusters/ssptools.git
Keywords: ssptools
Classifier: Development Status :: 4 - Beta
Classifier: Programming Language :: Python
Classifier: Intended Audience :: Science/Research
Classifier: Topic :: Scientific/Engineering :: Astronomy
Requires-Python: >=3.10
License-File: LICENSE
Requires-Dist: numpy
Requires-Dist: scipy
Provides-Extra: test
Requires-Dist: pytest; extra == "test"
Requires-Dist: cosmic-popsynth; extra == "test"
Dynamic: license-file
